[
  {
    "id": 1,
    "title": "Home",
    "to": "home"
  },

  {
    "id": 2,
    "title": "About",
    "to": "about"
  },

  {
    "id": 3,
    "title": "Architecture",
    "to": "architecture"
  },

  {
    "id": 4,
    "title": "Design",
    "to": "design"
  },

  {
    "id": 5,
    "title": "Data Flow",
    "to": "data_flow"
  },

  {
    "id": 6,
    "title": "Team",
    "to": "team"
  },

  {
    "id": 7,
    "title": "Testimonials",
    "to": "testimonials"
  },

  {
    "id": 8,
    "title": "Blogs",
    "to": "blogs"
  }
]
